multi_dash/README.md
multi_dash/__init__.py
multi_dash/dummy_authentication.py
multi_dash/index/__init__.py
multi_dash/index/templates/multi_dash/example_base.html.j2
multi_dash/index/templates/multi_dash/inline_scripts.js
multi_dash-0.2.0.dist-info/WHEEL
multi_dash-0.2.0.dist-info/METADATA
multi_dash-0.2.0.dist-info/RECORD
