Metadata-Version: 2.1
Name: multi-dash
Version: 0.2.0
Summary: A light framework to make multi-page dash based apps.
License: MIT
Author: James Saunders
Author-email: james@businessoptics.biz
Requires-Python: >=3.7,<4.0
Classifier: License :: OSI Approved :: MIT License
Classifier: Programming Language :: Python :: 3
Classifier: Programming Language :: Python :: 3.7
Classifier: Programming Language :: Python :: 3.8
